{
  "day": 5,
  "topic": "There .. and It ",
  "sections": [
    {
      "title": "Introduction",
      "content": "Welcome to Unit 84 of our English learning journey. In this unit, we'll explore the usage of 'there' and 'it' in various contexts. "
    },
    {
      "title": "Definition",
      "content": "Understanding how to use these placeholders is crucial for constructing clear and coherent sentences. Let's delve into the key concepts"
    },
    {
      "title": "There",
      "content": "'There' as a Placeholder",
      "points": [
        "Understand how 'there' is used as a placeholder to indicate the existence or presence of something.",
        "There is a cat in the garden",
        "There are many books on the shelf"
      ]
    },
    {
      "title": "It",
      "content": "'It' as a Placeholder",
      "points": [
        "Explore the use of 'it' as a placeholder to represent a general idea, time, or weather.",
        "It is important to be punctual.",
        "It is raining outside"
      ]
    },
    {
      "title": "Examples",
      "content": "Let's examine examples to illustrate the application of 'there' and 'it'",
      "points": [
          "There are flowers in the vase",
          "It is difficult to learn a new language",
          "There is a party at my friend's house",
          "It is sunny today"
      ]
    },
    {
      "title": "Usage and Content",
      "content": "Understand the appropriate contexts for using 'there' and 'it' and how they contribute to the structure and meaning of a sentence."
    },
    {
      "title": "Recap and Summary:",
      "content": "In summary, using 'there' and 'it' as placeholders enhances sentence structure and clarity in various situations."
    },
    {
      "title": "Additional Resources:",
      "content": "For additional practice and reinforcement, consider exploring examples in language learning books and online exercises."
    },
    {
      "title": "Conclusion",
      "content": "Thank you for joining today's lesson on 'There  and It ' Practice using these placeholders confidently in various situations, and feel free to reach out if you have any questions. Happy learning"
    }
  ]
}